{
  "versions": [
    {
      "git-tree": "7c113e12089453e4e2cf2bbf67ad1f0b80a133a8",
      "version": "0.98.1",
      "port-version": 6
    },
    {
      "git-tree": "0419d2f293a094dc4cdca1111daea2a6425a137b",
      "version": "0.98.1",
      "port-version": 5
    },
    {
      "git-tree": "98925560fbceb14da7820146f6df113f9dae7988",
      "version-string": "0.98.1",
      "port-version": 4
    },
    {
      "git-tree": "5c54a762a232fdd14c8b3c945715aaee5efcfa33",
      "version-string": "0.98.1",
      "port-version": 3
    },
    {
      "git-tree": "9a6fd5bed1b925ba8b4d12372a3f6d6b48535165",
      "version-string": "0.98.1-2",
      "port-version": 0
    },
    {
      "git-tree": "1b7b591e35ba71d91bc6e91642f8e1831c1bba3c",
      "version-string": "0.98.1-1",
      "port-version": 0
    },
    {
      "git-tree": "a302d636d8a6122c64d1193fa45fd62d22695e50",
      "version-string": "0.98.1",
      "port-version": 0
    }
  ]
}
