{
  "name": "sqlgen",
  "version": "0.1.0",
  "description": "sqlgen is an ORM and SQL query generator for C++-20, similar to Python's SQLAlchemy/SQLModel or Rust's Diesel.",
  "homepage": "https://github.com/getml/sqlgen/",
  "license": "MIT",
  "dependencies": [
    {
      "name": "reflectcpp"
    },
    {
      "name": "vcpkg-cmake",
      "host": true
    },
    {
      "name": "vcpkg-cmake-config",
      "host": true
    }
  ],
  "features": {
    "postgres": {
      "description": "Enable PostgreSQL support",
      "dependencies": [
        {
          "name": "libpq"
        }
      ]
    },
    "sqlite3": {
      "description": "Enable SQLite3 support",
      "dependencies": [
        {
          "name": "sqlite3",
          "features": [
            "math"
          ]
        }
      ]
    },
    "tests": {
      "description": "Build the tests",
      "dependencies": [
        {
          "name": "gtest"
        }
      ]
    }
  }
}
