{
  "versions": [
    {
      "git-tree": "bb9e0ae36b74ecd5bfb6a8855e761138eeda9185",
      "version": "20230531",
      "port-version": 0
    },
    {
      "git-tree": "6f1bed68940353855027de67f5f6d33c5dbe8617",
      "version": "20200924",
      "port-version": 4
    },
    {
      "git-tree": "4947aeed6f0e7817a4be646bbb7685e4e5ebf62a",
      "version": "20200924",
      "port-version": 3
    },
    {
      "git-tree": "8154d9ed8e6458688478aae1e09c2334362bc198",
      "version": "20200924",
      "port-version": 2
    },
    {
      "git-tree": "5fd24bb27699940f72b94a9c3cf3e77a7d645a76",
      "version-string": "20200924",
      "port-version": 1
    },
    {
      "git-tree": "a32a36b9ae670a8b20449ec2ef9283a6fbcf1a5e",
      "version-string": "20200924",
      "port-version": 0
    }
  ]
}
