{
  "versions": [
    {
      "git-tree": "df755dc18bda1d4c02a54db6cef63e46021ce872",
      "version-semver": "0.3.19",
      "port-version": 1
    },
    {
      "git-tree": "126bfc519dc0c50fc52ed0b19a0bd88663bae87f",
      "version-semver": "0.3.19",
      "port-version": 0
    },
    {
      "git-tree": "e574f424edd5d2fd9ca36c5058f96163d9018725",
      "version-semver": "0.3.18",
      "port-version": 0
    },
    {
      "git-tree": "0bc5be29ebb8c6a63883d7e76fab6c2613273384",
      "version-semver": "0.3.17",
      "port-version": 0
    },
    {
      "git-tree": "e98d775d36ccb84c9ffa20e2cf6f8ef1b7ab0461",
      "version-semver": "0.2.6",
      "port-version": 0
    }
  ]
}
