{
  "versions": [
    {
      "git-tree": "b0e352bf9c678b6425f767a21470b2c8ef3f79b9",
      "version": "1.0.0",
      "port-version": 5
    },
    {
      "git-tree": "ec66f22ef7f9e652008269b8419a34350d97accf",
      "version": "1.0.0",
      "port-version": 4
    },
    {
      "git-tree": "1bd9454fd218a1755ab651e97769f69b2d2fc315",
      "version-string": "1.0.0-3",
      "port-version": 0
    },
    {
      "git-tree": "045ef786b9d3a2d5d9f1096f118cf6e39ea08c79",
      "version-string": "1.0.0-2",
      "port-version": 0
    },
    {
      "git-tree": "0af6f1b35db62fd52bd0695a03ec69679ce2fb80",
      "version-string": "1.0.0-1",
      "port-version": 0
    },
    {
      "git-tree": "473af71f3b2014e34d957eede82178f3ae6272a5",
      "version-string": "1.0.0",
      "port-version": 0
    },
    {
      "git-tree": "4706465acae9a157a820b098c357712a8d098545",
      "version-string": "0.3.0-6",
      "port-version": 0
    },
    {
      "git-tree": "cb846a419ab42b35851532b4f2d2b637ea9f0d86",
      "version-string": "0.3.0-5",
      "port-version": 0
    },
    {
      "git-tree": "c3e824a15cc586e34d76eca9f6f84f24c924a67c",
      "version-string": "0.3.0-4",
      "port-version": 0
    },
    {
      "git-tree": "8ae50f8349189772fd4acf8c68125634aaffbe6e",
      "version-string": "0.3.0-3",
      "port-version": 0
    }
  ]
}
