{
  "name": "soundtouch",
  "version": "2.3.2",
  "description": "SoundTouch is an open-source audio processing library for changing the Tempo, Pitch and Playback Rates of audio streams or audio files.",
  "homepage": "https://www.surina.net/soundtouch",
  "supports": "!uwp",
  "dependencies": [
    {
      "name": "atlmfc",
      "platform": "windows"
    },
    {
      "name": "vcpkg-cmake",
      "host": true
    },
    {
      "name": "vcpkg-cmake-config",
      "host": true
    }
  ],
  "features": {
    "soundstretch": {
      "description": "Build the soundstretch command line tool"
    },
    "soundtouchdll": {
      "description": "Build the SoundTouchDLL C wrapper dynamic library"
    }
  }
}
