{
  "versions": [
    {
      "git-tree": "8f535672e2935cbbf33bd2a3f332d3a100cf6a4a",
      "version-date": "2019-11-30",
      "port-version": 4
    },
    {
      "git-tree": "b0593649089167c5e7e5e8da3d48dc20bbb0e366",
      "version-string": "2019-11-30",
      "port-version": 3
    },
    {
      "git-tree": "ca6e7889f9ae5d1d9a627d7591e22962cde621c4",
      "version-string": "2019-11-30",
      "port-version": 2
    },
    {
      "git-tree": "a83a72b6737956e551fe4ddbaa12564048141cec",
      "version-string": "2019-11-30",
      "port-version": 1
    },
    {
      "git-tree": "507af996ff26bc000fd73761de24f58be61507bd",
      "version-string": "2019-11-30",
      "port-version": 0
    }
  ]
}
