{
  "versions": [
    {
      "git-tree": "25c84663d7fe9c5010bfc7baf2ad7c1c70c5c429",
      "version-date": "2023-11-24",
      "port-version": 1
    },
    {
      "git-tree": "7b8009fe2173eac9490fd50428585a19cd85b043",
      "version-date": "2023-11-24",
      "port-version": 0
    },
    {
      "git-tree": "748c91a2ed90cad10b92d4c527dc855ec8f15db0",
      "version": "1.6",
      "port-version": 1
    },
    {
      "git-tree": "9f204819a5063dea81b56369e5ce424219e56ca5",
      "version": "1.6",
      "port-version": 0
    }
  ]
}
