{
  "$comment": "Automatically generated by scripts/boost/generate-ports.ps1",
  "name": "boost-metaparse",
  "version": "1.81.0",
  "port-version": 1,
  "description": "Boost metaparse module",
  "homepage": "https://github.com/boostorg/metaparse",
  "license": "BSL-1.0",
  "dependencies": [
    {
      "name": "boost-config",
      "version>=": "1.81.0#1"
    },
    {
      "name": "boost-mpl",
      "version>=": "1.81.0#1"
    },
    {
      "name": "boost-predef",
      "version>=": "1.81.0#1"
    },
    {
      "name": "boost-preprocessor",
      "version>=": "1.81.0#1"
    },
    {
      "name": "boost-static-assert",
      "version>=": "1.81.0#1"
    },
    {
      "name": "boost-type-traits",
      "version>=": "1.81.0#1"
    },
    {
      "name": "boost-vcpkg-helpers",
      "version>=": "1.81.0#2"
    }
  ]
}
