{
  "versions": [
    {
      "git-tree": "bb172f7bc0075f17c4b1c9f1068adfbb2bc4b3a8",
      "version": "1.1.82.1",
      "port-version": 3
    },
    {
      "git-tree": "693b2d999097790fec95ae3dae5d3b9054052d57",
      "version-string": "1.1.82.1",
      "port-version": 2
    },
    {
      "git-tree": "50baea2e993e948b8477929a7f600da93991224b",
      "version-string": "1.1.82.1-1",
      "port-version": 0
    },
    {
      "git-tree": "7c914e2fbbea69fe95f83236d1b1ccfd9739e735",
      "version-string": "1.1.82.1",
      "port-version": 0
    }
  ]
}
